kite_common/__init__.py
kite_common/base.py
kite_common/countries.py
kite_common/currencies.py
kite_common/error_codes.py
kite_common/languages.py
kite_common/timezones.py
kite_common/data/countries.json
kite_common/data/currencies.json
kite_common/data/error_codes.json
kite_common/data/languages.json
kite_common/data/timezones.json
kite_common_py-0.0.1.dist-info/licenses/LICENSE
scripts/__init__.py
scripts/extract_sql_data.py
kite_common_py-0.0.1.dist-info/METADATA
kite_common_py-0.0.1.dist-info/WHEEL
kite_common_py-0.0.1.dist-info/top_level.txt
kite_common_py-0.0.1.dist-info/RECORD
