Metadata-Version: 2.4
Name: kite-common-py
Version: 0.0.1
Summary: Kite Common Python Package
Home-page: https://github.com/kite/kite-common-py
Author: Addy
Author-email: Addy <adityag7077@gmail.com>
Project-URL: Homepage, https://github.com/kite/kite-common-py
Classifier: Programming Language :: Python :: 3
Classifier: License :: OSI Approved :: MIT License
Classifier: Operating System :: OS Independent
Requires-Python: >=3.8
License-File: LICENSE
Dynamic: author
Dynamic: home-page
Dynamic: license-file
Dynamic: requires-python
